{
  "name": "Suzy's Brain Garden",
  "subtitle": "A collection of my thoughts and ideas.",
  "description": "A collection of my thoughts and ideas.",
  "footer": "Made with ❤ by Suzy",
  "url": "https://suzys-brain-garden.netlify.app",
  "githubUrl": "https://github.com/adventurebear/suzys-brain-garden",
  "githubBranch": "main",
  "navigationStyle": "vertical",
  "emoji": "💥",
  "enableSearch": true,
  "enableDarkMode": true,
  "enableEditButton": true,
  "enableDatestamp": true,
  "enableGithubLink": false,
  "enableContact": false,
  "enableNetlifyCMS": false,
  "enableComments": false,
  "enableEncryption": false,
  "enablePageNavigation": false
}
